embody/__init__.py
embody/graphviz_template.py
embody/naming.py
embody-0.0.2.dist-info/LICENSE
embody-0.0.2.dist-info/METADATA
embody-0.0.2.dist-info/WHEEL
embody-0.0.2.dist-info/top_level.txt
embody-0.0.2.dist-info/RECORD
