Metadata-Version: 2.1
Name: embody
Version: 0.0.2
Summary: Generate templated objects
Home-page: https://github.com/thorwhalen/embody
Author: Thor Whalen
License: apache-2.0
Platform: any
Requires-Dist: dol
